{
  "ProtocolSection": {
    "IdentificationModule": {
      "NCTId": "NCT01207661",
      "OrgStudyIdInfo": {
        "OrgStudyId": "Royan-Bone-002"
      },
      "Organization": {
        "OrgFullName": "Royan Institute",
        "OrgClass": "OTHER_GOV"
      },
      "BriefTitle": "Articular Cartilage Resurfacing With Mesenchymal Stem Cells In Osteoarthritis Of Knee Joint",
      "OfficialTitle": "Mesenchymal Stem Cells Transplantation for Articular Cartilage Resurfacing in Patient With Osteoarthritis of Knee Joint"
    },
    "StatusModule": {
      "StatusVerifiedDate": "April 2009",
      "OverallStatus": "Completed",
      "ExpandedAccessInfo": {
        "HasExpandedAccess": "No"
      },
      "StartDateStruct": {
        "StartDate": "August 2009"
      },
      "PrimaryCompletionDateStruct": {
        "PrimaryCompletionDate": "July 2010",
        "PrimaryCompletionDateType": "Actual"
      },
      "CompletionDateStruct": {
        "CompletionDate": "November 2010",
        "CompletionDateType": "Actual"
      },
      "StudyFirstSubmitDate": "September 6, 2010",
      "StudyFirstSubmitQCDate": "September 22, 2010",
      "StudyFirstPostDateStruct": {
        "StudyFirstPostDate": "September 23, 2010",
        "StudyFirstPostDateType": "Estimate"
      },
      "LastUpdateSubmitDate": "January 2, 2012",
      "LastUpdatePostDateStruct": {
        "LastUpdatePostDate": "January 5, 2012",
        "LastUpdatePostDateType": "Estimate"
      }
    },
    "SponsorCollaboratorsModule": {
      "ResponsibleParty": {
        "ResponsiblePartyType": "Sponsor"
      },
      "LeadSponsor": {
        "LeadSponsorName": "Royan Institute",
        "LeadSponsorClass": "OTHER_GOV"
      }
    },
    "OversightModule": {
      "OversightHasDMC": "Yes"
    },
    "DescriptionModule": {
      "BriefSummary": "Knee osteoarthritis is the most common form of arthritis. Treatments involve high costs in terms of social and economic, are palliative and do not contemplate healing by regenerative therapy. It has been shown recently, that mesenchymal stem cells (MSC) can be expanded in vitro and may regenerate several damaged or injured tissues. In addition its has demonstrated that MSC are able to modulate immune responses and to control inflammation through its action on T lymphocytes. Preliminary studies in animal models, including one carried out in an equine by the investigators research group, confirms feasibility, safety and efficacy evidence proposed treatment protocol.This study is designed to evaluate therapeutic potential and safety of mesenchymal stem cells in improvement of osteoarthritis clinical manifestations.This study is designed to evaluate therapeutic potential and safety of mesenchymal stem cells in improvement of osteoarthritis clinical manifestations.",
      "DetailedDescription": "Mesenchymal stem cells are pluripotent cells that can be obtained from various tissues .They have shown capabilities to differentiate into bone,cartilage,muscle,and adipose tissue, representing a new clinical strategy in regenerative medicine.An increasing number of reports have demonstrated effectiveness of percutaneous intra-articular infusion of MSCs in arthritic disease. In this study we perform a single intra articular injection of cultured mesenchymal stem cells in patients suffering from osteoarthritis, with the aim to assess its clinical safety and efficacy.Patients are assessed for response with MRI, X-Ray examination, WOMAC osteoarthritis index,VAS, and SF36 2,4,8 weeks and 6, and 12 months post infusion."
    },
    "ConditionsModule": {
      "ConditionList": {
        "Condition": [
          "Osteoarthritis"
        ]
      },
      "KeywordList": {
        "Keyword": [
          "Mesenchymal cells",
          "osteoarthritis",
          "intra articular injection"
        ]
      }
    },
    "DesignModule": {
      "StudyType": "Interventional",
      "PhaseList": {
        "Phase": [
          "Phase 1"
        ]
      },
      "DesignInfo": {
        "DesignAllocation": "N/A",
        "DesignInterventionModel": "Single Group Assignment",
        "DesignPrimaryPurpose": "Treatment",
        "DesignMaskingInfo": {
          "DesignMasking": "None (Open Label)"
        }
      },
      "EnrollmentInfo": {
        "EnrollmentCount": "6",
        "EnrollmentType": "Actual"
      }
    },
    "ArmsInterventionsModule": {
      "ArmGroupList": {
        "ArmGroup": [
          {
            "ArmGroupLabel": "Mesenchymal Injection",
            "ArmGroupType": "Experimental",
            "ArmGroupDescription": "Intra Articular injection in Patients with osteoarthritis of knee joint",
            "ArmGroupInterventionList": {
              "ArmGroupInterventionName": [
                "Biological: Mesenchymal Injection"
              ]
            }
          }
        ]
      },
      "InterventionList": {
        "Intervention": [
          {
            "InterventionType": "Biological",
            "InterventionName": "Mesenchymal Injection",
            "InterventionDescription": "Intra Articular Injection of Mesenchymal cells to the knee joint",
            "InterventionArmGroupLabelList": {
              "InterventionArmGroupLabel": [
                "Mesenchymal Injection"
              ]
            },
            "InterventionOtherNameList": {
              "InterventionOtherName": [
                "Cell Injection"
              ]
            }
          }
        ]
      }
    },
    "OutcomesModule": {
      "PrimaryOutcomeList": {
        "PrimaryOutcome": [
          {
            "PrimaryOutcomeMeasure": "Pain relief",
            "PrimaryOutcomeDescription": "evaluation the effect of Mesenchymal stem cell transplantation to decrease the patients pain",
            "PrimaryOutcomeTimeFrame": "6 months"
          }
        ]
      },
      "SecondaryOutcomeList": {
        "SecondaryOutcome": [
          {
            "SecondaryOutcomeMeasure": "Pain relief",
            "SecondaryOutcomeDescription": "decrease the patient pain in VAS scale",
            "SecondaryOutcomeTimeFrame": "6 months"
          }
        ]
      }
    },
    "EligibilityModule": {
      "EligibilityCriteria": "Inclusion Criteria:\n\nFemale patients not pregnant or lactating.\nPatients with a history of corticosteroids or on active therapy, will only be eligible for enrollment if corticosteroid use is suspended for 1 month prior cell therapy\nMarcaine 0.75% و Lidocaine 4% test performed to be assure the exact location of the pain is related to the knee.\nDiagnosis must be based on magnetic resonance imaging.\nBoth genders\nAge:18-65 years\n\nExclusion Criteria:\n\nDiagnosis of cancer,DM,CNS disorder,thyroid disease or respiratory disease.\nKnown allergic reaction to components of study treatment and/or study injection procedure\nPatients infected with hepatitis B,C or HIV.",
      "HealthyVolunteers": "No",
      "Gender": "All",
      "MinimumAge": "18 Years",
      "MaximumAge": "65 Years",
      "StdAgeList": {
        "StdAge": [
          "Adult",
          "Older Adult"
        ]
      }
    },
    "ContactsLocationsModule": {
      "OverallOfficialList": {
        "OverallOfficial": [
          {
            "OverallOfficialName": "Hamid Gourabi, PhD",
            "OverallOfficialAffiliation": "Head of Royan Institute",
            "OverallOfficialRole": "Study Chair"
          },
          {
            "OverallOfficialName": "Mohammad reza Baghban Eslami Nejad, PhD",
            "OverallOfficialAffiliation": "Scientific Board",
            "OverallOfficialRole": "Study Director"
          },
          {
            "OverallOfficialName": "Mohssen Emadeddin, MD",
            "OverallOfficialAffiliation": "Orthopadic Investigator",
            "OverallOfficialRole": "Principal Investigator"
          },
          {
            "OverallOfficialName": "Nasser Aghdami, MD,PhD",
            "OverallOfficialAffiliation": "Head of Regeneration center",
            "OverallOfficialRole": "Principal Investigator"
          }
        ]
      },
      "LocationList": {
        "Location": [
          {
            "LocationFacility": "Royan Institute",
            "LocationCity": "Tehran",
            "LocationCountry": "Iran, Islamic Republic of"
          }
        ]
      }
    },
    "ReferencesModule": {
      "ReferenceList": {
        "Reference": [
          {
            "ReferencePMID": "26058927",
            "ReferenceType": "derived",
            "ReferenceCitation": "Emadedin M, Ghorbani Liastani M, Fazeli R, Mohseni F, Moghadasali R, Mardpour S, Hosseini SE, Niknejadi M, Moeininia F, Aghahossein Fanni A, Baghban Eslaminejhad R, Vosough Dizaji A, Labibzadeh N, Mirazimi Bafghi A, Baharvand H, Aghdami N. Long-Term Follow-up of Intra-articular Injection of Autologous Mesenchymal Stem Cells in Patients with Knee, Ankle, or Hip Osteoarthritis. Arch Iran Med. 2015 Jun;18(6):336-44. doi: 015186/AIM.003."
          }
        ]
      },
      "SeeAlsoLinkList": {
        "SeeAlsoLink": [
          {
            "SeeAlsoLinkLabel": "Related Info",
            "SeeAlsoLinkURL": "http://www.royaninstitute.org"
          }
        ]
      }
    }
  },
  "DerivedSection": {
    "MiscInfoModule": {
      "VersionHolder": "January 20, 2022"
    },
    "ConditionBrowseModule": {
      "ConditionMeshList": {
        "ConditionMesh": [
          {
            "ConditionMeshId": "D000010003",
            "ConditionMeshTerm": "Osteoarthritis"
          },
          {
            "ConditionMeshId": "D000020370",
            "ConditionMeshTerm": "Osteoarthritis, Knee"
          }
        ]
      },
      "ConditionAncestorList": {
        "ConditionAncestor": [
          {
            "ConditionAncestorId": "D000001168",
            "ConditionAncestorTerm": "Arthritis"
          },
          {
            "ConditionAncestorId": "D000007592",
            "ConditionAncestorTerm": "Joint Diseases"
          },
          {
            "ConditionAncestorId": "D000009140",
            "ConditionAncestorTerm": "Musculoskeletal Diseases"
          },
          {
            "ConditionAncestorId": "D000012216",
            "ConditionAncestorTerm": "Rheumatic Diseases"
          }
        ]
      },
      "ConditionBrowseLeafList": {
        "ConditionBrowseLeaf": [
          {
            "ConditionBrowseLeafId": "M12078",
            "ConditionBrowseLeafName": "Osteoarthritis",
            "ConditionBrowseLeafAsFound": "Osteoarthritis",
            "ConditionBrowseLeafRelevance": "high"
          },
          {
            "ConditionBrowseLeafId": "M21321",
            "ConditionBrowseLeafName": "Osteoarthritis, Knee",
            "ConditionBrowseLeafAsFound": "Osteoarthritis of Knee",
            "ConditionBrowseLeafRelevance": "high"
          },
          {
            "ConditionBrowseLeafId": "M3628",
            "ConditionBrowseLeafName": "Arthritis",
            "ConditionBrowseLeafRelevance": "low"
          },
          {
            "ConditionBrowseLeafId": "M9773",
            "ConditionBrowseLeafName": "Joint Diseases",
            "ConditionBrowseLeafRelevance": "low"
          },
          {
            "ConditionBrowseLeafId": "M11249",
            "ConditionBrowseLeafName": "Musculoskeletal Diseases",
            "ConditionBrowseLeafRelevance": "low"
          },
          {
            "ConditionBrowseLeafId": "M14197",
            "ConditionBrowseLeafName": "Rheumatic Diseases",
            "ConditionBrowseLeafRelevance": "low"
          },
          {
            "ConditionBrowseLeafId": "M5475",
            "ConditionBrowseLeafName": "Collagen Diseases",
            "ConditionBrowseLeafRelevance": "low"
          }
        ]
      },
      "ConditionBrowseBranchList": {
        "ConditionBrowseBranch": [
          {
            "ConditionBrowseBranchAbbrev": "BC05",
            "ConditionBrowseBranchName": "Musculoskeletal Diseases"
          },
          {
            "ConditionBrowseBranchAbbrev": "All",
            "ConditionBrowseBranchName": "All Conditions"
          },
          {
            "ConditionBrowseBranchAbbrev": "BC17",
            "ConditionBrowseBranchName": "Skin and Connective Tissue Diseases"
          }
        ]
      }
    }
  }
}