{
  "ProtocolSection": {
    "IdentificationModule": {
      "NCTId": "NCT02834858",
      "OrgStudyIdInfo": {
        "OrgStudyId": "ThirdSouthernMedical1"
      },
      "Organization": {
        "OrgFullName": "The Third Affiliated Hospital of Southern Medical University",
        "OrgClass": "OTHER_GOV"
      },
      "BriefTitle": "Umbilical Cord Mesenchymal Stem Cells Infusion for Diabetes Related Vascular Complications",
      "OfficialTitle": "Umbilical Cord Mesenchymal Stem Cells Infusion for Diabetes Related Vascular Complications"
    },
    "StatusModule": {
      "StatusVerifiedDate": "April 2017",
      "OverallStatus": "Unknown status",
      "LastKnownStatus": "Recruiting",
      "ExpandedAccessInfo": {
        "HasExpandedAccess": "No"
      },
      "StartDateStruct": {
        "StartDate": "January 2016"
      },
      "PrimaryCompletionDateStruct": {
        "PrimaryCompletionDate": "December 2018",
        "PrimaryCompletionDateType": "Anticipated"
      },
      "CompletionDateStruct": {
        "CompletionDate": "December 2019",
        "CompletionDateType": "Anticipated"
      },
      "StudyFirstSubmitDate": "July 9, 2016",
      "StudyFirstSubmitQCDate": "July 14, 2016",
      "StudyFirstPostDateStruct": {
        "StudyFirstPostDate": "July 15, 2016",
        "StudyFirstPostDateType": "Estimate"
      },
      "LastUpdateSubmitDate": "April 4, 2017",
      "LastUpdatePostDateStruct": {
        "LastUpdatePostDate": "April 6, 2017",
        "LastUpdatePostDateType": "Actual"
      }
    },
    "SponsorCollaboratorsModule": {
      "ResponsibleParty": {
        "ResponsiblePartyType": "Sponsor-Investigator",
        "ResponsiblePartyInvestigatorFullName": "Jie Shen",
        "ResponsiblePartyInvestigatorTitle": "doctor",
        "ResponsiblePartyInvestigatorAffiliation": "The Third Affiliated Hospital of Southern Medical University"
      },
      "LeadSponsor": {
        "LeadSponsorName": "Jie Shen",
        "LeadSponsorClass": "OTHER_GOV"
      },
      "CollaboratorList": {
        "Collaborator": [
          {
            "CollaboratorName": "Nanfang Hospital of Southern Medical University",
            "CollaboratorClass": "OTHER"
          },
          {
            "CollaboratorName": "Academy Military Medical Science, China",
            "CollaboratorClass": "INDUSTRY"
          },
          {
            "CollaboratorName": "The Fifth Affiliated Hospital of Southern Medical University",
            "CollaboratorClass": "OTHER"
          },
          {
            "CollaboratorName": "Southern Medical University, China",
            "CollaboratorClass": "OTHER"
          }
        ]
      }
    },
    "OversightModule": {
      "OversightHasDMC": "Yes"
    },
    "DescriptionModule": {
      "BriefSummary": "Stem cell therapy has been a new and effective therapy in recent years for diabetic foot.This study intends to establish an optimal clinical research program, and attempts to break the technical bottleneck in the stem cell therapy for treating diabetes related vascular complications.",
      "DetailedDescription": "Diabetic foot is one of the most serious chronic complications of diabetic patients, and still lacking effective treatments.\n\nStem cell therapy has been a new and effective therapy in recent years for diabetic foot. Combined with the previous studies of the investigators research group, this study intends to transform part of the results of this research, establish an optimal clinical research program, and attempts to break the technical bottleneck in the stem cell therapy for treating diabetes related vascular complications."
    },
    "ConditionsModule": {
      "ConditionList": {
        "Condition": [
          "Peripheral Vascular Disease",
          "Ischemia",
          "Diabetic Foot"
        ]
      },
      "KeywordList": {
        "Keyword": [
          "Umbilical Cord Mesenchymal Stem Cells"
        ]
      }
    },
    "DesignModule": {
      "StudyType": "Interventional",
      "PhaseList": {
        "Phase": [
          "Phase 1"
        ]
      },
      "DesignInfo": {
        "DesignAllocation": "Randomized",
        "DesignInterventionModel": "Parallel Assignment",
        "DesignPrimaryPurpose": "Treatment",
        "DesignMaskingInfo": {
          "DesignMasking": "None (Open Label)"
        }
      },
      "EnrollmentInfo": {
        "EnrollmentCount": "240",
        "EnrollmentType": "Anticipated"
      }
    },
    "ArmsInterventionsModule": {
      "ArmGroupList": {
        "ArmGroup": [
          {
            "ArmGroupLabel": "Umbilical Cord Mesenchymal Stem Cells",
            "ArmGroupType": "Experimental",
            "ArmGroupDescription": "Umbilical Cord Mesenchymal Stem Cells Infusion.",
            "ArmGroupInterventionList": {
              "ArmGroupInterventionName": [
                "Biological: Umbilical Cord Mesenchymal Stem Cells"
              ]
            }
          },
          {
            "ArmGroupLabel": "saline",
            "ArmGroupType": "Placebo Comparator",
            "ArmGroupDescription": "saline injection",
            "ArmGroupInterventionList": {
              "ArmGroupInterventionName": [
                "Biological: saline"
              ]
            }
          }
        ]
      },
      "InterventionList": {
        "Intervention": [
          {
            "InterventionType": "Biological",
            "InterventionName": "Umbilical Cord Mesenchymal Stem Cells",
            "InterventionDescription": "stem cell acquisition, processing and reinfection, to evaluate the efficacy by using umbilical cord mesenchymal stem cells",
            "InterventionArmGroupLabelList": {
              "InterventionArmGroupLabel": [
                "Umbilical Cord Mesenchymal Stem Cells"
              ]
            }
          },
          {
            "InterventionType": "Biological",
            "InterventionName": "saline",
            "InterventionArmGroupLabelList": {
              "InterventionArmGroupLabel": [
                "saline"
              ]
            }
          }
        ]
      }
    },
    "OutcomesModule": {
      "PrimaryOutcomeList": {
        "PrimaryOutcome": [
          {
            "PrimaryOutcomeMeasure": "Area of diabetic foot ulcers",
            "PrimaryOutcomeDescription": "To determine the ability of MSC to facilitate and accelerate diabetic foot ulcers healing.",
            "PrimaryOutcomeTimeFrame": "3 months"
          }
        ]
      },
      "SecondaryOutcomeList": {
        "SecondaryOutcome": [
          {
            "SecondaryOutcomeMeasure": "Improvement of transcutaneous oxygen partial pressure (TcPO2)",
            "SecondaryOutcomeDescription": "Improvement of local perfusion.",
            "SecondaryOutcomeTimeFrame": "3 months"
          },
          {
            "SecondaryOutcomeMeasure": "Improvement of microvascular cutaneous reactivity by laser Doppler perfusion monitoring (LDPM)",
            "SecondaryOutcomeTimeFrame": "3 months"
          },
          {
            "SecondaryOutcomeMeasure": "Pain (Visual-Analog Scale)",
            "SecondaryOutcomeDescription": "Measure of the subjective symptom of pain.",
            "SecondaryOutcomeTimeFrame": "3 months"
          },
          {
            "SecondaryOutcomeMeasure": "Walking distance (treadmill) if possible",
            "SecondaryOutcomeTimeFrame": "3 months"
          }
        ]
      }
    },
    "EligibilityModule": {
      "EligibilityCriteria": "Inclusion Criteria:\n\nDiabetes mellitus Type 2 or Type 1\nAge between 18-80 years\nChronic foot ulcer more than 6 weeks\nNo sufficient response to best standard care delivered for six weeks.\nPAD up to Fontaine stage III or IV period\nCLI with the ankle brachial index (index ankle-brachial, ABI) <0.7 and (or) the percutaneous oxygen partial pressure (oxygen tension transcutaneous, TcPO2) <30mmHg\n\nExclusion Criteria:\n\nHbA1c >12%\nHemoglobin <10 mg/dl\nCreatinine clearance rate <30ml/min\nSystemic bacterial, viral infections (Mei Du, hepatitis, cytomegalovirus infection, - HIV, B19 infection, herpes virus infection) and sepsis\nHave accepted the treatment of stem cells or growth factors\nHave a history of malignant disease\nPregnancy\nMental illness history\nAbnormal coagulation function\nAllergic reaction\nSevere cardiac insufficiency (III-IV NYHA)\nUsing vasoactive substances",
      "HealthyVolunteers": "No",
      "Gender": "All",
      "MinimumAge": "18 Years",
      "MaximumAge": "80 Years",
      "StdAgeList": {
        "StdAge": [
          "Adult",
          "Older Adult"
        ]
      }
    },
    "ContactsLocationsModule": {
      "CentralContactList": {
        "CentralContact": [
          {
            "CentralContactName": "Jie Shen",
            "CentralContactRole": "Contact",
            "CentralContactPhone": "+86 13808893818",
            "CentralContactEMail": "shenjiedr@163.com"
          }
        ]
      },
      "OverallOfficialList": {
        "OverallOfficial": [
          {
            "OverallOfficialName": "Jie Shen",
            "OverallOfficialAffiliation": "The Third Affiliated Hospital of Southern Medical University",
            "OverallOfficialRole": "Principal Investigator"
          }
        ]
      },
      "LocationList": {
        "Location": [
          {
            "LocationFacility": "the Third Affiliated Hospital of Southern Medical University",
            "LocationStatus": "Recruiting",
            "LocationCity": "Guangzhou",
            "LocationState": "Guangdong",
            "LocationZip": "510515",
            "LocationCountry": "China",
            "LocationContactList": {
              "LocationContact": [
                {
                  "LocationContactName": "zhang qun",
                  "LocationContactRole": "Contact",
                  "LocationContactPhone": "020-62784060",
                  "LocationContactEMail": "Zq1979@smu.edu.cn"
                },
                {
                  "LocationContactName": "Jie Shen",
                  "LocationContactRole": "Sub-Investigator"
                }
              ]
            }
          }
        ]
      }
    },
    "IPDSharingStatementModule": {
      "IPDSharing": "Undecided"
    }
  },
  "DerivedSection": {
    "MiscInfoModule": {
      "VersionHolder": "January 20, 2022"
    },
    "ConditionBrowseModule": {
      "ConditionMeshList": {
        "ConditionMesh": [
          {
            "ConditionMeshId": "D000017719",
            "ConditionMeshTerm": "Diabetic Foot"
          },
          {
            "ConditionMeshId": "D000014652",
            "ConditionMeshTerm": "Vascular Diseases"
          },
          {
            "ConditionMeshId": "D000016491",
            "ConditionMeshTerm": "Peripheral Vascular Diseases"
          },
          {
            "ConditionMeshId": "D000058729",
            "ConditionMeshTerm": "Peripheral Arterial Disease"
          },
          {
            "ConditionMeshId": "D000007511",
            "ConditionMeshTerm": "Ischemia"
          }
        ]
      },
      "ConditionAncestorList": {
        "ConditionAncestor": [
          {
            "ConditionAncestorId": "D000010335",
            "ConditionAncestorTerm": "Pathologic Processes"
          },
          {
            "ConditionAncestorId": "D000003925",
            "ConditionAncestorTerm": "Diabetic Angiopathies"
          },
          {
            "ConditionAncestorId": "D000002318",
            "ConditionAncestorTerm": "Cardiovascular Diseases"
          },
          {
            "ConditionAncestorId": "D000016523",
            "ConditionAncestorTerm": "Foot Ulcer"
          },
          {
            "ConditionAncestorId": "D000007871",
            "ConditionAncestorTerm": "Leg Ulcer"
          },
          {
            "ConditionAncestorId": "D000012883",
            "ConditionAncestorTerm": "Skin Ulcer"
          },
          {
            "ConditionAncestorId": "D000012871",
            "ConditionAncestorTerm": "Skin Diseases"
          },
          {
            "ConditionAncestorId": "D000048909",
            "ConditionAncestorTerm": "Diabetes Complications"
          },
          {
            "ConditionAncestorId": "D000003920",
            "ConditionAncestorTerm": "Diabetes Mellitus"
          },
          {
            "ConditionAncestorId": "D000004700",
            "ConditionAncestorTerm": "Endocrine System Diseases"
          },
          {
            "ConditionAncestorId": "D000003929",
            "ConditionAncestorTerm": "Diabetic Neuropathies"
          },
          {
            "ConditionAncestorId": "D000050197",
            "ConditionAncestorTerm": "Atherosclerosis"
          },
          {
            "ConditionAncestorId": "D000001161",
            "ConditionAncestorTerm": "Arteriosclerosis"
          },
          {
            "ConditionAncestorId": "D000001157",
            "ConditionAncestorTerm": "Arterial Occlusive Diseases"
          }
        ]
      },
      "ConditionBrowseLeafList": {
        "ConditionBrowseLeaf": [
          {
            "ConditionBrowseLeafId": "M6267",
            "ConditionBrowseLeafName": "Diabetes Mellitus",
            "ConditionBrowseLeafRelevance": "low"
          },
          {
            "ConditionBrowseLeafId": "M16552",
            "ConditionBrowseLeafName": "Vascular Diseases",
            "ConditionBrowseLeafAsFound": "Vascular Disease",
            "ConditionBrowseLeafRelevance": "high"
          },
          {
            "ConditionBrowseLeafId": "M9695",
            "ConditionBrowseLeafName": "Ischemia",
            "ConditionBrowseLeafAsFound": "Ischemia",
            "ConditionBrowseLeafRelevance": "high"
          },
          {
            "ConditionBrowseLeafId": "M19085",
            "ConditionBrowseLeafName": "Diabetic Foot",
            "ConditionBrowseLeafAsFound": "Diabetic Foot",
            "ConditionBrowseLeafRelevance": "high"
          },
          {
            "ConditionBrowseLeafId": "M28366",
            "ConditionBrowseLeafName": "Peripheral Arterial Disease",
            "ConditionBrowseLeafAsFound": "Peripheral Vascular Disease",
            "ConditionBrowseLeafRelevance": "high"
          },
          {
            "ConditionBrowseLeafId": "M18046",
            "ConditionBrowseLeafName": "Peripheral Vascular Diseases",
            "ConditionBrowseLeafAsFound": "Peripheral Vascular Disease",
            "ConditionBrowseLeafRelevance": "high"
          },
          {
            "ConditionBrowseLeafId": "M6272",
            "ConditionBrowseLeafName": "Diabetic Angiopathies",
            "ConditionBrowseLeafRelevance": "low"
          },
          {
            "ConditionBrowseLeafId": "M16358",
            "ConditionBrowseLeafName": "Ulcer",
            "ConditionBrowseLeafRelevance": "low"
          },
          {
            "ConditionBrowseLeafId": "M18071",
            "ConditionBrowseLeafName": "Foot Ulcer",
            "ConditionBrowseLeafRelevance": "low"
          },
          {
            "ConditionBrowseLeafId": "M10035",
            "ConditionBrowseLeafName": "Leg Ulcer",
            "ConditionBrowseLeafRelevance": "low"
          },
          {
            "ConditionBrowseLeafId": "M14838",
            "ConditionBrowseLeafName": "Skin Ulcer",
            "ConditionBrowseLeafRelevance": "low"
          },
          {
            "ConditionBrowseLeafId": "M14826",
            "ConditionBrowseLeafName": "Skin Diseases",
            "ConditionBrowseLeafRelevance": "low"
          },
          {
            "ConditionBrowseLeafId": "M25157",
            "ConditionBrowseLeafName": "Diabetes Complications",
            "ConditionBrowseLeafRelevance": "low"
          },
          {
            "ConditionBrowseLeafId": "M7014",
            "ConditionBrowseLeafName": "Endocrine System Diseases",
            "ConditionBrowseLeafRelevance": "low"
          },
          {
            "ConditionBrowseLeafId": "M6276",
            "ConditionBrowseLeafName": "Diabetic Neuropathies",
            "ConditionBrowseLeafRelevance": "low"
          },
          {
            "ConditionBrowseLeafId": "M25341",
            "ConditionBrowseLeafName": "Atherosclerosis",
            "ConditionBrowseLeafRelevance": "low"
          },
          {
            "ConditionBrowseLeafId": "M3621",
            "ConditionBrowseLeafName": "Arteriosclerosis",
            "ConditionBrowseLeafRelevance": "low"
          },
          {
            "ConditionBrowseLeafId": "M3617",
            "ConditionBrowseLeafName": "Arterial Occlusive Diseases",
            "ConditionBrowseLeafRelevance": "low"
          }
        ]
      },
      "ConditionBrowseBranchList": {
        "ConditionBrowseBranch": [
          {
            "ConditionBrowseBranchAbbrev": "BC18",
            "ConditionBrowseBranchName": "Nutritional and Metabolic Diseases"
          },
          {
            "ConditionBrowseBranchAbbrev": "BC19",
            "ConditionBrowseBranchName": "Gland and Hormone Related Diseases"
          },
          {
            "ConditionBrowseBranchAbbrev": "All",
            "ConditionBrowseBranchName": "All Conditions"
          },
          {
            "ConditionBrowseBranchAbbrev": "BC14",
            "ConditionBrowseBranchName": "Heart and Blood Diseases"
          },
          {
            "ConditionBrowseBranchAbbrev": "BC23",
            "ConditionBrowseBranchName": "Symptoms and General Pathology"
          },
          {
            "ConditionBrowseBranchAbbrev": "BC17",
            "ConditionBrowseBranchName": "Skin and Connective Tissue Diseases"
          },
          {
            "ConditionBrowseBranchAbbrev": "BC10",
            "ConditionBrowseBranchName": "Nervous System Diseases"
          }
        ]
      }
    }
  }
}