{
  "ProtocolSection": {
    "IdentificationModule": {
      "NCTId": "NCT03056742",
      "OrgStudyIdInfo": {
        "OrgStudyId": "SRPL/CLI/10-11/001 Version 4"
      },
      "Organization": {
        "OrgFullName": "Stempeutics Research Pvt Ltd",
        "OrgClass": "INDUSTRY"
      },
      "BriefTitle": "A Clinical Trial to Study the Efficacy and Safety of Stempeucel® in Patients With CLI Due to Buergers Disease",
      "OfficialTitle": "A Single Arm, Open Label, Multicentric, Clinical Study Assessing the Efficacy and Safety of Stempeucel® (ex Vivo Cultured Adult Bone Marrow Derived Allogeneic Mesenchymal Stem Cells) in Patients With CLI Due to Buerger's Disease"
    },
    "StatusModule": {
      "StatusVerifiedDate": "April 2017",
      "OverallStatus": "Withdrawn",
      "WhyStopped": "Form 46 from DCGI for the manufacturing & commercial marketing of Stempeucel® directs Stempeutics to conduct PMS study. Hence this study is being terminated.",
      "ExpandedAccessInfo": {
        "HasExpandedAccess": "No"
      },
      "StartDateStruct": {
        "StartDate": "February 20, 2017",
        "StartDateType": "Anticipated"
      },
      "PrimaryCompletionDateStruct": {
        "PrimaryCompletionDate": "April 2018",
        "PrimaryCompletionDateType": "Anticipated"
      },
      "CompletionDateStruct": {
        "CompletionDate": "October 2019",
        "CompletionDateType": "Anticipated"
      },
      "StudyFirstSubmitDate": "January 23, 2017",
      "StudyFirstSubmitQCDate": "February 14, 2017",
      "StudyFirstPostDateStruct": {
        "StudyFirstPostDate": "February 17, 2017",
        "StudyFirstPostDateType": "Actual"
      },
      "LastUpdateSubmitDate": "April 5, 2017",
      "LastUpdatePostDateStruct": {
        "LastUpdatePostDate": "April 7, 2017",
        "LastUpdatePostDateType": "Actual"
      }
    },
    "SponsorCollaboratorsModule": {
      "ResponsibleParty": {
        "ResponsiblePartyType": "Sponsor"
      },
      "LeadSponsor": {
        "LeadSponsorName": "Stempeutics Research Pvt Ltd",
        "LeadSponsorClass": "INDUSTRY"
      }
    },
    "OversightModule": {
      "OversightHasDMC": "Yes",
      "IsFDARegulatedDrug": "No",
      "IsFDARegulatedDevice": "No"
    },
    "DescriptionModule": {
      "BriefSummary": "This study is being conducted as an extension of the phase II clinical trial SRPL/CLI/10-11/001 (NCT01484574). The CDSCO has recommended flexibility for continued clinical study in consultation with ICMR, as per recommendation of Cellular biology based therapeutic drug evaluation committee (CBBTDEC).",
      "DetailedDescription": "This study will evaluate the safety and efficacy of intramuscular injection of stempeucel(R) (Ex vivo cultured adult bone marrow derived allogeneic mesenchymal stem cells) in Critical Limb Ischemia due to Buerger's Disease"
    },
    "ConditionsModule": {
      "ConditionList": {
        "Condition": [
          "Critical Limb Ischemia Due to Buerger's Disease"
        ]
      }
    },
    "DesignModule": {
      "StudyType": "Interventional",
      "PhaseList": {
        "Phase": [
          "Phase 2"
        ]
      },
      "DesignInfo": {
        "DesignAllocation": "N/A",
        "DesignInterventionModel": "Single Group Assignment",
        "DesignPrimaryPurpose": "Treatment",
        "DesignMaskingInfo": {
          "DesignMasking": "None (Open Label)"
        }
      },
      "EnrollmentInfo": {
        "EnrollmentCount": "0",
        "EnrollmentType": "Actual"
      }
    },
    "ArmsInterventionsModule": {
      "ArmGroupList": {
        "ArmGroup": [
          {
            "ArmGroupLabel": "Stem cells",
            "ArmGroupType": "Experimental",
            "ArmGroupDescription": "Patients will receive intramuscular and local injection of stempeucel(R) in addition to standard protocol of care",
            "ArmGroupInterventionList": {
              "ArmGroupInterventionName": [
                "Biological: Stempeucel(R)"
              ]
            }
          }
        ]
      },
      "InterventionList": {
        "Intervention": [
          {
            "InterventionType": "Biological",
            "InterventionName": "Stempeucel(R)",
            "InterventionDescription": "Ex vivo cultured adult bone marrow derived allogeneic mesenchymal stem cells",
            "InterventionArmGroupLabelList": {
              "InterventionArmGroupLabel": [
                "Stem cells"
              ]
            }
          }
        ]
      }
    },
    "OutcomesModule": {
      "PrimaryOutcomeList": {
        "PrimaryOutcome": [
          {
            "PrimaryOutcomeMeasure": "Relief of the rest pain",
            "PrimaryOutcomeTimeFrame": "6 months"
          },
          {
            "PrimaryOutcomeMeasure": "Reduction of ulcer area in the target limb",
            "PrimaryOutcomeTimeFrame": "6 months"
          }
        ]
      },
      "SecondaryOutcomeList": {
        "SecondaryOutcome": [
          {
            "SecondaryOutcomeMeasure": "Total walking distance",
            "SecondaryOutcomeTimeFrame": "6 months and 24 months"
          },
          {
            "SecondaryOutcomeMeasure": "Major amputation free survival",
            "SecondaryOutcomeTimeFrame": "6 months and 24 months"
          },
          {
            "SecondaryOutcomeMeasure": "Ankle brachial pressure index (ABPI) - measured by Doppler",
            "SecondaryOutcomeTimeFrame": "6 months and 24 months"
          },
          {
            "SecondaryOutcomeMeasure": "Quality of life (QOL) by King's College VascuQOL questionnaire",
            "SecondaryOutcomeTimeFrame": "6 months and 24 months"
          },
          {
            "SecondaryOutcomeMeasure": "Angiogenesis - collateral blood vessels by Magnetic resonance angiogram (MRA)",
            "SecondaryOutcomeTimeFrame": "6 months and 24 months"
          }
        ]
      },
      "OtherOutcomeList": {
        "OtherOutcome": [
          {
            "OtherOutcomeMeasure": "The type of adverse events AE(s), number of AE(s) and proportion of patients with AE(s).",
            "OtherOutcomeTimeFrame": "6 months and 24 months"
          },
          {
            "OtherOutcomeMeasure": "CVS mortality",
            "OtherOutcomeTimeFrame": "6 months and 24 months"
          },
          {
            "OtherOutcomeMeasure": "All-cause mortality",
            "OtherOutcomeTimeFrame": "6 months and 24 months"
          }
        ]
      }
    },
    "EligibilityModule": {
      "EligibilityCriteria": "Inclusion Criteria:\n\nBuerger's disease as diagnosed by Shionoya criteria\nMales or females (willing to use accepted methods of contraception during the course of the study) in the age group of 18-65 yrs.\nEstablished CLI in the study limb, clinically and hemodynamically confirmed as per Rutherford- III-5;\nPatients in Rutherford- III-6 if gangrene extending maximally up to the head of metatarsal but limited to toes (patients with wet gangrene must undergo wound debridement / amputation before screening) .\nPatients having infrapopliteal occlusive disease with rest pain and ischemic ulcer/necrosis (patients should have at least one measureable ulcer), who are not eligible for or have failed traditional revascularization treatment as per the investigators judgment (No option patients) .\nABPI ≤ 0.6 or ankle pressure ≤ 50 mm Hg.\nPatients who are able to understand the requirements of the study, and willing to provide voluntary written informed consent and video consent, abide by the study requirements, and agree to return for required follow-up visits.\n\nExclusion Criteria:\n\nPatients with CLI indicated for major amputation during screening\nAtherosclerotic PAD\nUlcers with exposure of tendon and/bone in the shin region.\nPrevious above trans metatarsal amputation in study limb\nAny Lumbar sympathectomy procedure performed less than 90 days prior to the screening\nPatients with gait disturbance for reasons other than CLI\nDiagnosis of diabetes mellitus (type 1 or type 2)\nPatients having left ventricular ejection fraction < 35%\nPatients suffering from clinically relevant peripheral neuropathy\nHistory of stroke or myocardial infarction\nPatients who are contraindicated for MRA\nPatients with DVT in any limb.\nPatients who have clinically serious and/or unstable inter-current infection, medical illnesses or conditions that are uncontrolled or whose control, in the opinion of the Investigator, may be jeopardized by participation in this study or by the complications of this therapy\nDocumented terminal illness or cancer or any concomitant disease process with a life expectancy of <1 year\nPatients already enrolled in another investigational drug trial or completed within 3 months or those who have received stem cells in the past\nPatient with known hypersensitivity to the constituents of the stempeucel®- dimethyl sulfoxide (DMSO) or human serum albumin (HSA)\nHistory of severe alcohol or drug abuse within 3 months of screening\nHb% < 10 gm% for males, Hb% < 9 gm% for females, serum creatinine ≥ 2mg%, serum Total Bilirubin ≥2mg%\nPregnant and lactating women\nPatients tested positive for HIV 1 & 2, HCV, HBV, CMV, RPR antibodies and for HBsAg antigen",
      "HealthyVolunteers": "No",
      "Gender": "All",
      "MinimumAge": "18 Years",
      "MaximumAge": "65 Years",
      "StdAgeList": {
        "StdAge": [
          "Adult",
          "Older Adult"
        ]
      }
    },
    "ContactsLocationsModule": {
      "LocationList": {
        "Location": [
          {
            "LocationFacility": "Department of Surgical Disciplines, All India Institute of Medical Sciences",
            "LocationCity": "New Delhi",
            "LocationState": "Delhi",
            "LocationZip": "110029",
            "LocationCountry": "India"
          },
          {
            "LocationFacility": "Department of Vascular and Endovascular Surgery, M. S. Ramaiah Medical College and Hospitals",
            "LocationCity": "Bangalore",
            "LocationState": "Karnataka",
            "LocationZip": "560066",
            "LocationCountry": "India"
          },
          {
            "LocationFacility": "Department of Vascular Surgery, Madras Medical College",
            "LocationCity": "Chennai",
            "LocationState": "Tamil Nadu",
            "LocationZip": "600003",
            "LocationCountry": "India"
          },
          {
            "LocationFacility": "Department of Vascular Surgery, Sri Ramchandra Medical College",
            "LocationCity": "Chennai",
            "LocationState": "Tamil Nadu",
            "LocationZip": "600116",
            "LocationCountry": "India"
          },
          {
            "LocationFacility": "Saveetha Medical College & Hospital",
            "LocationCity": "Chennai",
            "LocationState": "Tamil Nadu",
            "LocationZip": "602105",
            "LocationCountry": "India"
          },
          {
            "LocationFacility": "SRM Medical College Hospital and Research Centre",
            "LocationCity": "Chennai",
            "LocationState": "Tamil Nadu",
            "LocationZip": "603203",
            "LocationCountry": "India"
          },
          {
            "LocationFacility": "Health Point Hospital",
            "LocationCity": "Kolkata",
            "LocationState": "West Bengal",
            "LocationZip": "700025",
            "LocationCountry": "India"
          },
          {
            "LocationFacility": "Nightingale Hospital",
            "LocationCity": "Kolkata",
            "LocationState": "West Bengal",
            "LocationZip": "700071",
            "LocationCountry": "India"
          }
        ]
      }
    },
    "IPDSharingStatementModule": {
      "IPDSharing": "No"
    }
  },
  "DerivedSection": {
    "MiscInfoModule": {
      "VersionHolder": "January 20, 2022"
    },
    "ConditionBrowseModule": {
      "ConditionMeshList": {
        "ConditionMesh": [
          {
            "ConditionMeshId": "D000013919",
            "ConditionMeshTerm": "Thromboangiitis Obliterans"
          },
          {
            "ConditionMeshId": "D000007511",
            "ConditionMeshTerm": "Ischemia"
          }
        ]
      },
      "ConditionAncestorList": {
        "ConditionAncestor": [
          {
            "ConditionAncestorId": "D000010335",
            "ConditionAncestorTerm": "Pathologic Processes"
          },
          {
            "ConditionAncestorId": "D000001157",
            "ConditionAncestorTerm": "Arterial Occlusive Diseases"
          },
          {
            "ConditionAncestorId": "D000014652",
            "ConditionAncestorTerm": "Vascular Diseases"
          },
          {
            "ConditionAncestorId": "D000002318",
            "ConditionAncestorTerm": "Cardiovascular Diseases"
          },
          {
            "ConditionAncestorId": "D000014657",
            "ConditionAncestorTerm": "Vasculitis"
          }
        ]
      },
      "ConditionBrowseLeafList": {
        "ConditionBrowseLeaf": [
          {
            "ConditionBrowseLeafId": "M9695",
            "ConditionBrowseLeafName": "Ischemia",
            "ConditionBrowseLeafAsFound": "Ischemia",
            "ConditionBrowseLeafRelevance": "high"
          },
          {
            "ConditionBrowseLeafId": "M15830",
            "ConditionBrowseLeafName": "Thromboangiitis Obliterans",
            "ConditionBrowseLeafAsFound": "Buerger's Disease",
            "ConditionBrowseLeafRelevance": "high"
          },
          {
            "ConditionBrowseLeafId": "M3617",
            "ConditionBrowseLeafName": "Arterial Occlusive Diseases",
            "ConditionBrowseLeafRelevance": "low"
          },
          {
            "ConditionBrowseLeafId": "M16552",
            "ConditionBrowseLeafName": "Vascular Diseases",
            "ConditionBrowseLeafRelevance": "low"
          },
          {
            "ConditionBrowseLeafId": "M16557",
            "ConditionBrowseLeafName": "Vasculitis",
            "ConditionBrowseLeafRelevance": "low"
          },
          {
            "ConditionBrowseLeafId": "T889",
            "ConditionBrowseLeafName": "Buerger Disease",
            "ConditionBrowseLeafAsFound": "Buerger's Disease",
            "ConditionBrowseLeafRelevance": "high"
          }
        ]
      },
      "ConditionBrowseBranchList": {
        "ConditionBrowseBranch": [
          {
            "ConditionBrowseBranchAbbrev": "BC23",
            "ConditionBrowseBranchName": "Symptoms and General Pathology"
          },
          {
            "ConditionBrowseBranchAbbrev": "All",
            "ConditionBrowseBranchName": "All Conditions"
          },
          {
            "ConditionBrowseBranchAbbrev": "BC14",
            "ConditionBrowseBranchName": "Heart and Blood Diseases"
          },
          {
            "ConditionBrowseBranchAbbrev": "Rare",
            "ConditionBrowseBranchName": "Rare Diseases"
          }
        ]
      }
    }
  }
}